ai2_internal/__init__.py
ai2_internal/api.py
ai2_internal/bibentry_detection_predictor/__init__.py
ai2_internal/bibentry_detection_predictor/integration_test.py
ai2_internal/bibentry_detection_predictor/interface.py
ai2_internal/bibentry_detection_predictor/data/000026bab3c52aa8ff37dc3e155ffbcb506aa1f6.pdf
ai2_internal/bibentry_detection_predictor/data/no_bibs.pdf
ai2_internal/bibentry_detection_predictor/data/spanless_bibs_3cf45514384bbb7d083ae53e19bdc22300e648ab.pdf
ai2_internal/bibentry_predictor/__init__.py
ai2_internal/bibentry_predictor/integration_test.py
ai2_internal/bibentry_predictor/interface.py
ai2_internal/bibentry_predictor_mmda/__init__.py
ai2_internal/bibentry_predictor_mmda/integration_test.py
ai2_internal/bibentry_predictor_mmda/interface.py
ai2_internal/bibentry_predictor_mmda/data/test_data.json.gz
ai2_internal/bibentry_predictor_mmda/data/test_data_v2_first_2_bibs_have_empty_span_groups.json.gz
ai2_internal/citation_links/__init__.py
ai2_internal/citation_links/integration_test.py
ai2_internal/citation_links/interface.py
ai2_internal/citation_mentions/__init__.py
ai2_internal/citation_mentions/integration_test.py
ai2_internal/citation_mentions/interface.py
ai2_internal/citation_mentions/data/arxiv-1906.08632-page0.pdf
ai2_internal/citation_mentions/data/arxiv-1906.08632-pages1-2.pdf
ai2_internal/figure_table_predictors/__init__.py
ai2_internal/figure_table_predictors/integration_test.py
ai2_internal/figure_table_predictors/interface.py
ai2_internal/figure_table_predictors/test_fixtures/test_doc.json
ai2_internal/figure_table_predictors/test_fixtures/test_doc_sha_08f02e7888f140a76a00ed23fce2f2fc303a.json
ai2_internal/figure_table_predictors/test_fixtures/test_doc_sha_08f02e7888f140a76a00ed23fce2f2fc303a.pdf
ai2_internal/figure_table_predictors/test_fixtures/test_doc_sha_d0450478c38dda61f9943f417ab9fcdb2ebeae0a.json
ai2_internal/figure_table_predictors/test_fixtures/test_doc_sha_d0450478c38dda61f9943f417ab9fcdb2ebeae0a.pdf
mmda-0.4.8.dist-info/LICENSE
mmda-0.4.8.dist-info/METADATA
mmda-0.4.8.dist-info/WHEEL
mmda-0.4.8.dist-info/top_level.txt
mmda-0.4.8.dist-info/RECORD
